lovd/__init__.py
lovd/cli.py
lovd/client.py
lovd/config.py
lovd/constants.py
lovdtools-0.1.0.dev28.dist-info/METADATA
lovdtools-0.1.0.dev28.dist-info/WHEEL
lovdtools-0.1.0.dev28.dist-info/entry_points.txt
lovdtools-0.1.0.dev28.dist-info/licenses/LICENSE
lovdtools-0.1.0.dev28.dist-info/RECORD
