Metadata-Version: 2.4
Name: lovdtools
Version: 0.1.0.dev28
Dynamic: Author
Dynamic: Author-email
Summary: A fluent API client for the Global Variome shared LOVD instance.
License-Expression: MIT
License-File: LICENSE
Requires-Python: >=3.10
Requires-Dist: click>=8.3.1
Requires-Dist: numpy>=2.2.6
Requires-Dist: pandas>=2.3.3
Requires-Dist: platformdirs>=4.3.8
Requires-Dist: python-dotenv>=1.1.1
Requires-Dist: pyyaml>=6.0.2
Requires-Dist: requests>=2.32.4
Requires-Dist: tqdm>=4.67.1
